{"name":"test006","id":"in.reqres.reqresinfo.UserCURDTestWithSteps:test006","testCaseName":"in.reqres.reqresinfo.UserCURDTestWithSteps","testSteps":[{"number":1,"description":"Deleting user with ID 5","duration":205,"startTime":"2022-06-21T11:27:12.131+01:00[Europe/London]","result":"SUCCESS","precondition":false,"children":[{"number":2,"description":"DELETE https://reqres.in/api/users/5\r\r","duration":2,"startTime":"2022-06-21T11:27:12.334+01:00[Europe/London]","result":"SUCCESS","restQuery":{"method":"DELETE","path":"https://reqres.in/api/users/5\r\r","content":"\r","contentType":"null","requestHeaders":"Accept\u003d*/*\r\r","requestCookies":"\r\r","responseHeaders":"Date: Tue, 21 Jun 2022 10:27:07 GMT\nContent-Length: 0\nConnection: keep-alive\nX-Powered-By: Express\nAccess-Control-Allow-Origin: *\nEtag: W/\"2-vyGp6PvFo4RvsFtPoIWeCReyIC8\"\nVia: 1.1 vegur\nCF-Cache-Status: DYNAMIC\nExpect-CT: max-age\u003d604800, report-uri\u003d\"https://report-uri.cloudflare.com/cdn-cgi/beacon/expect-ct\"\nReport-To: {\"endpoints\":[{\"url\":\"https:\\/\\/a.nel.cloudflare.com\\/report\\/v3?s\u003dWZXKXegBFa6nmUK6%2FeNCrJ2N5tdQHq5amoYdzxgUhrymSEA88a%2FAIpB6j%2FfF0cZnDABlsICMrOwyQH%2BySZaSJRQaMJixNST7D0hY97aPpqp%2Baev0aQMEMLzhIg%3D%3D\"}],\"group\":\"cf-nel\",\"max_age\":604800}\nNEL: {\"success_fraction\":0,\"report_to\":\"cf-nel\",\"max_age\":604800}\nServer: cloudflare\nCF-RAY: 71ec0cc63f477738-LHR\r","responseCookies":"\r","statusCode":204},"precondition":false}]}],"userStory":{"id":"in.reqres.reqresinfo.UserCURDTestWithSteps","storyName":"User CURD test with steps","storyClassName":"in.reqres.reqresinfo.UserCURDTestWithSteps","path":"in.reqres.reqresinfo","type":"story"},"featureTag":{"name":"Reqresinfo/User CURD test with steps","type":"story"},"title":"This will Delete a user ","tags":[{"name":"Reqresinfo/User CURD test with steps","type":"story"}],"startTime":"2022-06-21T11:27:12.130+01:00[Europe/London]","duration":208,"projectKey":"","manual":false,"testSource":"JUnit","result":"SUCCESS"}